[
  {
    "date": "2026-02-17",
    "content": "年初一，下午去了同庆街看灯会，在大马旁边拍了很多照片，团团半途喝酸奶不喝配方奶了；今天还巧遇了李广。"
  },
  {
    "date": "2026-02-18",
    "content": "去了圆明园，人太多了，团团喝了酸奶也喝了配方奶；鞋子总掉。"
  },
  {
    "date": "2026-02-19",
    "content": "下午去了生命科学园的合生汇，建筑布局太乱了，没找到捞鱼的地方，差评"
  },
  {
    "date": "2026-02-20",
    "content": "小叔一家4口来玩，团团2点多起来了不认生，不哭，只是观察。"
  },
  {
    "date": "2026-02-21",
    "content": "到清河万象汇买鞋，还是江博士的鞋好一些，方便近期学步，顺便吃了炒冰激凌。"
  },
  {
    "date": "2026-02-22",
    "content": "下午来了昌发展，爸妈看了《惊蛰无声》，团团看了鹦鹉兔子仓鼠，还玩了游乐场，可开心了。"
  },
  {
    "date": "2026-02-23",
    "content": "到爸爸糖动物农场来看小动物，看到了兔子、绵羊、小马、鸡鸭鹅等，团团很爱玩沙子，人挺少，停车地方有的是。但是回去之后不好好吃饭6点直接睡了"
  }
]